{
  "main": {
    "id": "ee56b3ab0d4742fe",
    "type": "split",
    "children": [
      {
        "id": "bd1dbed7f9fc8f70",
        "type": "tabs",
        "children": [
          {
            "id": "b3d32e5537af17cb",
            "type": "leaf",
            "pinned": true,
            "state": {
              "type": "markdown",
              "state": {
                "file": "input.md",
                "mode": "preview",
                "source": false
              },
              "pinned": true,
              "icon": "lucide-file",
              "title": "input"
            }
          },
          {
            "id": "24bebac9c1a3d87c",
            "type": "leaf",
            "state": {
              "type": "markdown",
              "state": {
                "file": "atlas/map.md",
                "mode": "source",
                "source": false
              },
              "icon": "lucide-file",
              "title": "map"
            }
          }
        ],
        "currentTab": 1,
        "stacked": true
      }
    ],
    "direction": "vertical"
  },
  "left": {
    "id": "b9b589b6ff68fd65",
    "type": "split",
    "children": [
      {
        "id": "2e163179eaea93bc",
        "type": "tabs",
        "children": [
          {
            "id": "159202f2c28d4d5f",
            "type": "leaf",
            "state": {
              "type": "file-explorer",
              "state": {
                "sortOrder": "alphabetical",
                "autoReveal": false
              },
              "icon": "lucide-folder-closed",
              "title": "Files"
            }
          },
          {
            "id": "38f09e7bc41dc98e",
            "type": "leaf",
            "state": {
              "type": "search",
              "state": {
                "query": "#todo",
                "matchingCase": false,
                "explainSearch": false,
                "collapseAll": false,
                "extraContext": false,
                "sortOrder": "alphabetical"
              },
              "icon": "lucide-search",
              "title": "Search"
            }
          },
          {
            "id": "fd339f85a4000c3a",
            "type": "leaf",
            "state": {
              "type": "bookmarks",
              "state": {},
              "icon": "lucide-bookmark",
              "title": "Bookmarks"
            }
          }
        ]
      }
    ],
    "direction": "horizontal",
    "width": 241
  },
  "right": {
    "id": "8234af46590e440d",
    "type": "split",
    "children": [
      {
        "id": "58601a8b8dc306ac",
        "type": "tabs",
        "children": [
          {
            "id": "86543038554ca8af",
            "type": "leaf",
            "state": {
              "type": "tag",
              "state": {
                "sortOrder": "frequency",
                "useHierarchy": true,
                "showSearch": false,
                "searchQuery": ""
              },
              "icon": "lucide-tags",
              "title": "Tags"
            }
          },
          {
            "id": "e1dfdb849e0f107c",
            "type": "leaf",
            "state": {
              "type": "outline",
              "state": {
                "file": "Living off the Land.md",
                "followCursor": false,
                "showSearch": false,
                "searchQuery": ""
              },
              "icon": "lucide-list",
              "title": "Outline of Living off the Land"
            }
          },
          {
            "id": "bf8947d36879671b",
            "type": "leaf",
            "state": {
              "type": "file-properties",
              "state": {
                "file": "atlas/map.md"
              },
              "icon": "lucide-info",
              "title": "File properties for map"
            }
          },
          {
            "id": "b6fc942bbbbc2dcf",
            "type": "leaf",
            "state": {
              "type": "backlink",
              "state": {
                "file": "cards/red-team/Evading Logging and Monitoring.md",
                "collapseAll": false,
                "extraContext": false,
                "sortOrder": "alphabetical",
                "showSearch": false,
                "searchQuery": "",
                "backlinkCollapsed": false,
                "unlinkedCollapsed": true
              },
              "icon": "links-coming-in",
              "title": "Backlinks for Evading Logging and Monitoring"
            }
          },
          {
            "id": "4cceaa69e9e5b504",
            "type": "leaf",
            "state": {
              "type": "all-properties",
              "state": {
                "sortOrder": "frequency",
                "showSearch": false,
                "searchQuery": ""
              },
              "icon": "lucide-archive",
              "title": "All properties"
            }
          }
        ],
        "currentTab": 2
      }
    ],
    "direction": "horizontal",
    "width": 312,
    "collapsed": true
  },
  "left-ribbon": {
    "hiddenItems": {
      "bases:Create new base": false,
      "switcher:Open quick switcher": false,
      "graph:Open graph view": false,
      "canvas:Create new canvas": false,
      "daily-notes:Open today's daily note": false,
      "templates:Insert template": false,
      "command-palette:Open command palette": false,
      "digitalgarden:Digital Garden Publication Center": false,
      "obsidian-excalidraw-plugin:New drawing": false,
      "omnisearch:Omnisearch": false
    }
  },
  "active": "24bebac9c1a3d87c",
  "lastOpenFiles": [
    "input.md",
    "atlas/map.md",
    "Unpublished Notes.md",
    "atlas/dots.md",
    "notes.md",
    "cards/dots/Hybrid Encrpytion.md",
    "cards/blue-team/malware-analysis/Specimens/RAT.ReverseShell.exe.md",
    "cards/dots/Public Key Infrastructure (PKI).md",
    "cards/networking/Transport Layer Security.md",
    "cards/networking/images/TLS handshake.png",
    "cards/networking/TLS handshake.md",
    "cards/dots/Certificate Authority.md",
    "cards/networking/images/The threeway handshake.png",
    "cards/networking/images/The threeway handshake-1.png",
    "cards/networking/The threeway handshake.md",
    "cards/dots/Asymmetric Encryption.md",
    "atlas/networking.md",
    "cards/dots/images/Public Key Infrastructure (PKI)-1.png",
    "cards/dots/images/Public Key Infrastructure (PKI)-2.png",
    "cards/dots/images/Public Key Infrastructure (PKI).png",
    "cards/red-team/Network Security Solutions.md",
    "cards/red-team/images/Network Security Solutions-3.png",
    "cards/red-team/images/Network Security Solutions-2.png",
    "cards/red-team/images/Network Security Solutions-1.png",
    "cards/red-team/images/Network Security Solutions.png",
    "+/Windows Internals for Security Practitioners.md",
    "Vault Rules.md",
    "cards/windows/Windows Internals.md",
    "cards/dots/Pointers in C.md",
    "cards/dots/images",
    "cards/dots",
    "cards/concepts/Digital Oceans Writing Guidelines.md",
    "atlas/red-team.md",
    "atlas/active-directory.md",
    "cards/active-directory/Active Directory Enumeration.md",
    "atlas/blue-team.md",
    "cards/red-team/Evading Logging and Monitoring.md",
    "cards/red-team/Signature Evasion.md",
    "z_archive",
    "cards/networking/images",
    "cards/networking",
    "map-of-contents/Untitled",
    "cards/blue-team/malware-analysis/images",
    "cards/blue-team/malware-analysis/Untitled Folder",
    "cards/blue-team/malware-analysis/wannacry.yar",
    "cards/blue-team/malware-analysis/Specimens",
    "Space.canvas"
  ]
}